crawl_photos.py
crawl_photos-0.3.dev0.data/scripts/crawl_photos.py
crawl_photos-0.3.dev0.dist-info/LICENSE
crawl_photos-0.3.dev0.dist-info/METADATA
crawl_photos-0.3.dev0.dist-info/WHEEL
crawl_photos-0.3.dev0.dist-info/entry_points.txt
crawl_photos-0.3.dev0.dist-info/top_level.txt
crawl_photos-0.3.dev0.dist-info/RECORD
