Metadata-Version: 2.1
Name: crawl-photos
Version: 0.3.dev0
Summary: a test
Home-page: https://github.com/mcwt/crawl_photos
Author: mcwT
Author-email: 1830mm@sina.com
License: MIT
Platform: UNKNOWN
